{
    "origin": {
        "productor": "Agencia Estatal de Meteorología - AEMET. Gobierno de España",
        "web": "https://www.aemet.es",
        "language": "es",
        "copyright": "© AEMET. Autorizado el uso de la información y su reproducción citando a AEMET como autora de la misma.",
        "nota_legal": "https://www.aemet.es/es/nota_legal",
        "descripcion": "elTiempo.net muestra la información meteorológica creada por © AEMET"
    },
    "title": "elTiempo.net | El tiempo en Vitoria-Gasteiz (Araba/Álava)",
    "metadescripcion": "El tiempo en Vitoria-Gasteiz (Araba/Álava)",
    "keywords": "Vitoria-Gasteiz, Provincia de Ã\u0081lava, previsión meteorológica, previsión del tiempo, España, viento, humedad, precipitaciones, lluvia, estado del cielo",
    "municipio": {
        "CODIGOINE": "01059000000",
        "ID_REL": "1010590",
        "COD_GEO": "01001",
        "CODPROV": "01",
        "NOMBRE_PROVINCIA": "Araba/Álava",
        "NOMBRE": "Vitoria-Gasteiz",
        "POBLACION_MUNI": 242082,
        "SUPERFICIE": 27681.2008,
        "PERIMETRO": 111412,
        "CODIGOINE_CAPITAL": "01059006301",
        "NOMBRE_CAPITAL": "Vitoria-Gasteiz",
        "POBLACION_CAPITAL": "237092",
        "HOJA_MTN25": "0112-4",
        "LONGITUD_ETRS89_REGCAN95": -2.67275685,
        "LATITUD_ETRS89_REGCAN95": 42.85058789,
        "ORIGEN_COORD": "Mapa",
        "ALTITUD": 539,
        "ORIGEN_ALTITUD": "MDT5",
        "DISCREPANTE_INE": 0
    },
    "fecha": "2024-04-15",
    "stateSky": {
        "description": "Cubierto",
        "id": "16n"
    },
    "temperatura_actual": "11",
    "temperaturas": {
        "max": "16",
        "min": "7"
    },
    "humedad": "76",
    "viento": "16",
    "precipitacion": "0",
    "lluvia": "100",
    "imagen": null,
    "pronostico": {
        "hoy": {
            "@attributes": {
                "fecha": "2024-04-15",
                "orto": "07:28",
                "ocaso": "20:53"
            },
            "estado_cielo": [
                "46",
                "16",
                "16",
                "15",
                "15",
                "16",
                "46",
                "16n",
                "16n",
                "16n"
            ],
            "precipitacion": [
                "0.1",
                "0",
                "0",
                "0",
                "0",
                "0",
                "0.1",
                "0",
                "0",
                "0"
            ],
            "prob_precipitacion": [
                "100",
                "90"
            ],
            "prob_tormenta": [
                "0",
                "0"
            ],
            "nieve": [
                "0",
                "0",
                "0",
                "0",
                "0",
                "0",
                "0",
                "0",
                "0",
                "0"
            ],
            "prob_nieve": [
                "0",
                "0"
            ],
            "temperatura": [
                "14",
                "14",
                "14",
                "14",
                "13",
                "12",
                "11",
                "10",
                "9"
            ],
            "sens_termica": [
                "14",
                "14",
                "14",
                "14",
                "13",
                "12",
                "11",
                "10",
                "6"
            ],
            "humedad_relativa": [
                "73",
                "72",
                "70",
                "71",
                "71",
                "71",
                "76",
                "78",
                "78"
            ],
            "viento": [
                {
                    "@attributes": {
                        "periodo": "15"
                    },
                    "direccion": "N",
                    "velocidad": "16"
                },
                {
                    "@attributes": {
                        "periodo": "16"
                    },
                    "direccion": "N",
                    "velocidad": "16"
                },
                {
                    "@attributes": {
                        "periodo": "17"
                    },
                    "direccion": "N",
                    "velocidad": "16"
                },
                {
                    "@attributes": {
                        "periodo": "18"
                    },
                    "direccion": "N",
                    "velocidad": "17"
                },
                {
                    "@attributes": {
                        "periodo": "19"
                    },
                    "direccion": "N",
                    "velocidad": "16"
                },
                {
                    "@attributes": {
                        "periodo": "20"
                    },
                    "direccion": "N",
                    "velocidad": "16"
                },
                {
                    "@attributes": {
                        "periodo": "21"
                    },
                    "direccion": "N",
                    "velocidad": "16"
                },
                {
                    "@attributes": {
                        "periodo": "22"
                    },
                    "direccion": "N",
                    "velocidad": "17"
                },
                {
                    "@attributes": {
                        "periodo": "23"
                    },
                    "direccion": "N",
                    "velocidad": "19"
                }
            ],
            "racha_max": [
                "28",
                "29",
                "29",
                "28",
                "26",
                "26",
                "27",
                "30",
                "27"
            ],
            "estado_cielo_descripcion": [
                "Cubierto con lluvia escasa",
                "Cubierto",
                "Cubierto",
                "Muy nuboso",
                "Muy nuboso",
                "Cubierto",
                "Cubierto con lluvia escasa",
                "Cubierto",
                "Cubierto",
                "Cubierto"
            ]
        },
        "manana": {
            "@attributes": {
                "fecha": "2024-04-16",
                "orto": "07:26",
                "ocaso": "20:55"
            },
            "estado_cielo": [
                "16n",
                "16n",
                "16n",
                "16n",
                "16n",
                "16n",
                "16n",
                "16n",
                "16",
                "16",
                "46",
                "46",
                "46",
                "46",
                "46",
                "46",
                "46",
                "46",
                "16",
                "16",
                "16",
                "46n",
                "46n",
                "46n"
            ],
            "precipitacion": [
                "0",
                "0",
                "0",
                "0",
                "0",
                "0",
                "0",
                "0",
                "0",
                "0",
                "0.2",
                "0.2",
                "0.2",
                "0.1",
                "0.1",
                "0.1",
                "0.1",
                "0.1",
                "0",
                "0",
                "0",
                "0.1",
                "0.3",
                "0.3"
            ],
            "prob_precipitacion": [
                "35",
                "100",
                "100",
                "100"
            ],
            "prob_tormenta": [
                "0",
                "0",
                "0",
                "0"
            ],
            "nieve": [
                "0",
                "0",
                "0",
                "0",
                "0",
                "0",
                "0",
                "0",
                "0",
                "0",
                "0",
                "0",
                "0",
                "0",
                "0",
                "0",
                "0",
                "0",
                "0",
                "0",
                "0",
                "0",
                "0",
                "0"
            ],
            "prob_nieve": [
                "0",
                "0",
                "0",
                "0"
            ],
            "temperatura": [
                "9",
                "8",
                "7",
                "7",
                "6",
                "7",
                "7",
                "8",
                "8",
                "8",
                "9",
                "9",
                "10",
                "10",
                "11",
                "11",
                "11",
                "11",
                "10",
                "10",
                "10",
                "9",
                "8",
                "8"
            ],
            "sens_termica": [
                "6",
                "6",
                "5",
                "5",
                "6",
                "7",
                "7",
                "8",
                "6",
                "6",
                "7",
                "7",
                "10",
                "10",
                "11",
                "11",
                "11",
                "11",
                "10",
                "10",
                "10",
                "7",
                "6",
                "6"
            ],
            "humedad_relativa": [
                "81",
                "84",
                "85",
                "84",
                "86",
                "86",
                "86",
                "85",
                "85",
                "83",
                "86",
                "90",
                "86",
                "81",
                "78",
                "77",
                "77",
                "76",
                "77",
                "78",
                "79",
                "80",
                "81",
                "84"
            ],
            "viento": [
                {
                    "@attributes": {
                        "periodo": "00"
                    },
                    "direccion": "N",
                    "velocidad": "17"
                },
                {
                    "@attributes": {
                        "periodo": "01"
                    },
                    "direccion": "N",
                    "velocidad": "12"
                },
                {
                    "@attributes": {
                        "periodo": "02"
                    },
                    "direccion": "N",
                    "velocidad": "9"
                },
                {
                    "@attributes": {
                        "periodo": "03"
                    },
                    "direccion": "N",
                    "velocidad": "8"
                },
                {
                    "@attributes": {
                        "periodo": "04"
                    },
                    "direccion": "SO",
                    "velocidad": "2"
                },
                {
                    "@attributes": {
                        "periodo": "05"
                    },
                    "direccion": "O",
                    "velocidad": "5"
                },
                {
                    "@attributes": {
                        "periodo": "06"
                    },
                    "direccion": "NO",
                    "velocidad": "1"
                },
                {
                    "@attributes": {
                        "periodo": "07"
                    },
                    "direccion": "O",
                    "velocidad": "5"
                },
                {
                    "@attributes": {
                        "periodo": "08"
                    },
                    "direccion": "O",
                    "velocidad": "10"
                },
                {
                    "@attributes": {
                        "periodo": "09"
                    },
                    "direccion": "NO",
                    "velocidad": "10"
                },
                {
                    "@attributes": {
                        "periodo": "10"
                    },
                    "direccion": "NO",
                    "velocidad": "13"
                },
                {
                    "@attributes": {
                        "periodo": "11"
                    },
                    "direccion": "N",
                    "velocidad": "16"
                },
                {
                    "@attributes": {
                        "periodo": "12"
                    },
                    "direccion": "N",
                    "velocidad": "19"
                },
                {
                    "@attributes": {
                        "periodo": "13"
                    },
                    "direccion": "N",
                    "velocidad": "15"
                },
                {
                    "@attributes": {
                        "periodo": "14"
                    },
                    "direccion": "N",
                    "velocidad": "13"
                },
                {
                    "@attributes": {
                        "periodo": "15"
                    },
                    "direccion": "N",
                    "velocidad": "14"
                },
                {
                    "@attributes": {
                        "periodo": "16"
                    },
                    "direccion": "N",
                    "velocidad": "13"
                },
                {
                    "@attributes": {
                        "periodo": "17"
                    },
                    "direccion": "N",
                    "velocidad": "14"
                },
                {
                    "@attributes": {
                        "periodo": "18"
                    },
                    "direccion": "N",
                    "velocidad": "12"
                },
                {
                    "@attributes": {
                        "periodo": "19"
                    },
                    "direccion": "N",
                    "velocidad": "13"
                },
                {
                    "@attributes": {
                        "periodo": "20"
                    },
                    "direccion": "N",
                    "velocidad": "14"
                },
                {
                    "@attributes": {
                        "periodo": "21"
                    },
                    "direccion": "N",
                    "velocidad": "12"
                },
                {
                    "@attributes": {
                        "periodo": "22"
                    },
                    "direccion": "N",
                    "velocidad": "13"
                },
                {
                    "@attributes": {
                        "periodo": "23"
                    },
                    "direccion": "N",
                    "velocidad": "13"
                }
            ],
            "racha_max": [
                "22",
                "15",
                "17",
                "3",
                "10",
                "3",
                "8",
                "16",
                "19",
                "23",
                "26",
                "30",
                "25",
                "21",
                "22",
                "21",
                "22",
                "20",
                "20",
                "22",
                "19",
                "21",
                "21",
                "16"
            ],
            "estado_cielo_descripcion": [
                "Cubierto",
                "Cubierto",
                "Cubierto",
                "Cubierto",
                "Cubierto",
                "Cubierto",
                "Cubierto",
                "Cubierto",
                "Cubierto",
                "Cubierto",
                "Cubierto con lluvia escasa",
                "Cubierto con lluvia escasa",
                "Cubierto con lluvia escasa",
                "Cubierto con lluvia escasa",
                "Cubierto con lluvia escasa",
                "Cubierto con lluvia escasa",
                "Cubierto con lluvia escasa",
                "Cubierto con lluvia escasa",
                "Cubierto",
                "Cubierto",
                "Cubierto",
                "Cubierto con lluvia escasa",
                "Cubierto con lluvia escasa",
                "Cubierto con lluvia escasa"
            ]
        }
    },
    "proximos_dias": [
        {
            "@attributes": {
                "fecha": "2024-04-16"
            },
            "prob_precipitacion": [
                "100",
                "100",
                "100",
                "35",
                "100",
                "100",
                "100"
            ],
            "cota_nieve_prov": [
                "1400",
                {
                    "@attributes": {
                        "periodo": "00-12"
                    }
                },
                "1400",
                {
                    "@attributes": {
                        "periodo": "00-06"
                    }
                },
                {
                    "@attributes": {
                        "periodo": "06-12"
                    }
                },
                "1400",
                "1400"
            ],
            "estado_cielo": [
                "26",
                "26",
                "26",
                "16n",
                "26",
                "26",
                "26"
            ],
            "viento": [
                {
                    "@attributes": {
                        "periodo": "00-24"
                    },
                    "direccion": "N",
                    "velocidad": "15"
                },
                {
                    "@attributes": {
                        "periodo": "00-12"
                    },
                    "direccion": "N",
                    "velocidad": "15"
                },
                {
                    "@attributes": {
                        "periodo": "12-24"
                    },
                    "direccion": "N",
                    "velocidad": "15"
                },
                {
                    "@attributes": {
                        "periodo": "00-06"
                    },
                    "direccion": "O",
                    "velocidad": "10"
                },
                {
                    "@attributes": {
                        "periodo": "06-12"
                    },
                    "direccion": "N",
                    "velocidad": "15"
                },
                {
                    "@attributes": {
                        "periodo": "12-18"
                    },
                    "direccion": "N",
                    "velocidad": "15"
                },
                {
                    "@attributes": {
                        "periodo": "18-24"
                    },
                    "direccion": "NO",
                    "velocidad": "5"
                }
            ],
            "racha_max": [
                {
                    "@attributes": {
                        "periodo": "00-24"
                    }
                },
                {
                    "@attributes": {
                        "periodo": "00-12"
                    }
                },
                {
                    "@attributes": {
                        "periodo": "12-24"
                    }
                },
                {
                    "@attributes": {
                        "periodo": "00-06"
                    }
                },
                {
                    "@attributes": {
                        "periodo": "06-12"
                    }
                },
                {
                    "@attributes": {
                        "periodo": "12-18"
                    }
                },
                {
                    "@attributes": {
                        "periodo": "18-24"
                    }
                }
            ],
            "temperatura": {
                "maxima": "12",
                "minima": "6",
                "dato": [
                    "8",
                    "11",
                    "10",
                    "7"
                ]
            },
            "sens_termica": {
                "maxima": "12",
                "minima": "6",
                "dato": [
                    "6",
                    "11",
                    "10",
                    "7"
                ]
            },
            "humedad_relativa": {
                "maxima": "95",
                "minima": "75",
                "dato": [
                    "85",
                    "80",
                    "80",
                    "95"
                ]
            },
            "uv_max": "6",
            "estado_cielo_descripcion": [
                "Cubierto con lluvia",
                "Cubierto con lluvia",
                "Cubierto con lluvia",
                "Cubierto",
                "Cubierto con lluvia",
                "Cubierto con lluvia",
                "Cubierto con lluvia"
            ]
        },
        {
            "@attributes": {
                "fecha": "2024-04-17"
            },
            "prob_precipitacion": [
                "100",
                "100",
                "95"
            ],
            "cota_nieve_prov": [
                "1300",
                "1300",
                "1300"
            ],
            "estado_cielo": [
                "25",
                "25",
                "25"
            ],
            "viento": [
                {
                    "@attributes": {
                        "periodo": "00-24"
                    },
                    "direccion": "N",
                    "velocidad": "15"
                },
                {
                    "@attributes": {
                        "periodo": "00-12"
                    },
                    "direccion": "N",
                    "velocidad": "15"
                },
                {
                    "@attributes": {
                        "periodo": "12-24"
                    },
                    "direccion": "N",
                    "velocidad": "15"
                }
            ],
            "racha_max": [
                {
                    "@attributes": {
                        "periodo": "00-24"
                    }
                },
                {
                    "@attributes": {
                        "periodo": "00-12"
                    }
                },
                {
                    "@attributes": {
                        "periodo": "12-24"
                    }
                }
            ],
            "temperatura": {
                "maxima": "12",
                "minima": "5"
            },
            "sens_termica": {
                "maxima": "12",
                "minima": "5"
            },
            "humedad_relativa": {
                "maxima": "95",
                "minima": "65"
            },
            "uv_max": "6",
            "estado_cielo_descripcion": [
                "Muy nuboso con lluvia",
                "Muy nuboso con lluvia",
                "Muy nuboso con lluvia"
            ]
        },
        {
            "@attributes": {
                "fecha": "2024-04-18"
            },
            "prob_precipitacion": [
                "95",
                "90",
                "60"
            ],
            "cota_nieve_prov": [
                "1200",
                "1200",
                "1100"
            ],
            "estado_cielo": [
                "25",
                "26",
                "25"
            ],
            "viento": [
                {
                    "@attributes": {
                        "periodo": "00-24"
                    },
                    "direccion": "N",
                    "velocidad": "15"
                },
                {
                    "@attributes": {
                        "periodo": "00-12"
                    },
                    "direccion": "N",
                    "velocidad": "15"
                },
                {
                    "@attributes": {
                        "periodo": "12-24"
                    },
                    "direccion": "N",
                    "velocidad": "15"
                }
            ],
            "racha_max": [
                {
                    "@attributes": {
                        "periodo": "00-24"
                    }
                },
                {
                    "@attributes": {
                        "periodo": "00-12"
                    }
                },
                {
                    "@attributes": {
                        "periodo": "12-24"
                    }
                }
            ],
            "temperatura": {
                "maxima": "13",
                "minima": "2"
            },
            "sens_termica": {
                "maxima": "13",
                "minima": "2"
            },
            "humedad_relativa": {
                "maxima": "100",
                "minima": "55"
            },
            "uv_max": "5",
            "estado_cielo_descripcion": [
                "Muy nuboso con lluvia",
                "Cubierto con lluvia",
                "Muy nuboso con lluvia"
            ]
        },
        {
            "@attributes": {
                "fecha": "2024-04-19"
            },
            "prob_precipitacion": "20",
            "cota_nieve_prov": "1100",
            "estado_cielo": "13",
            "viento": {
                "direccion": "C",
                "velocidad": "0"
            },
            "racha_max": {},
            "temperatura": {
                "maxima": "19",
                "minima": "0"
            },
            "sens_termica": {
                "maxima": "19",
                "minima": "0"
            },
            "humedad_relativa": {
                "maxima": "100",
                "minima": "40"
            },
            "uv_max": "5",
            "estado_cielo_descripcion": "Intervalos nubosos"
        },
        {
            "@attributes": {
                "fecha": "2024-04-20"
            },
            "prob_precipitacion": "25",
            "cota_nieve_prov": "1300",
            "estado_cielo": "13",
            "viento": {
                "direccion": "N",
                "velocidad": "15"
            },
            "racha_max": {},
            "temperatura": {
                "maxima": "18",
                "minima": "3"
            },
            "sens_termica": {
                "maxima": "18",
                "minima": "3"
            },
            "humedad_relativa": {
                "maxima": "100",
                "minima": "45"
            },
            "estado_cielo_descripcion": "Intervalos nubosos"
        },
        {
            "@attributes": {
                "fecha": "2024-04-21"
            },
            "prob_precipitacion": "25",
            "cota_nieve_prov": "1300",
            "estado_cielo": "13",
            "viento": {
                "direccion": "N",
                "velocidad": "20"
            },
            "racha_max": {},
            "temperatura": {
                "maxima": "16",
                "minima": "4"
            },
            "sens_termica": {
                "maxima": "16",
                "minima": "4"
            },
            "humedad_relativa": {
                "maxima": "85",
                "minima": "45"
            },
            "estado_cielo_descripcion": "Intervalos nubosos"
        }
    ],
    "breadcrumb": [
        {
            "name": "Provincias",
            "url": "/provincias",
            "title": "El tiempo | Lista de provincias"
        },
        {
            "name": "Araba/Álava",
            "url": "/provincias/01",
            "title": "El tiempo en la provincia de Araba/Álava"
        },
        {
            "name": "Municipios",
            "url": "/provincias/01/municipios",
            "title": "El tiempo | Lista de municipios de Araba/Álava"
        },
        {
            "name": "Vitoria-Gasteiz",
            "url": "/provincias/01/municipios/01001",
            "title": "El tiempo en Vitoria-Gasteiz"
        }
    ]
}